{
  "vaultid": "ac639fe1-8bb0-40c6-9f03-7a6e7bb4832c",
  "keys": [
    "595d80ad-b4c0-4c17-ba1f-8dda500b664c"
  ],
  "rationale": "<p>Choice D is the best answer. &ldquo;Involved in&rdquo; means &ldquo;playing an active role in.&rdquo; This fits the context clues describing how Zollar includes the audience in her shows by incorporating their stories and pictures. </p><p>Choice A is incorrect. &ldquo;Nervous&rdquo; means &ldquo;worried or anxious about.&rdquo; Nothing in the text suggests that people would be nervous about Zollar&rsquo;s creative process. Choice B is incorrect. &ldquo;Completed by&rdquo; means &ldquo;made whole by.&rdquo; It doesn&rsquo;t make sense to say that Zollar&rsquo;s shows would make her audience complete. Choice C is incorrect. &ldquo;Delayed by&rdquo; means &ldquo;made late by.&rdquo; Nothing in the text suggests that people would be delayed by Zollar&rsquo;s creative process. </p>",
  "origin": "proteus",
  "stem": "<p>Which choice completes the text with the most logical and precise word or phrase?</p>",
  "externalid": "5f3280cd-e6b6-460d-9cd2-eff1f3095600",
  "stimulus": "<p>Dance choreographer Jawole Willa Jo Zollar aims to give people the opportunity to be <span aria-hidden=\"true\">______</span><span class=\"sr-only\">blank</span> her creative process. For example, live performances of her dance <em>HairStories</em>, which debuted in 2001, featured videos of people across the United States talking about their hair and audience members sharing pictures of their interesting hairstyles.</p>",
  "templateclusterid": "3671cc0e-9cf7-4f6a-bcb4-97f01fe17cba",
  "parenttemplatename": "OSP-KA-WIC-E006",
  "parenttemplateid": "",
  "type": "mcq",
  "position": "0",
  "templateclustername": "",
  "answerOptions": [
    {
      "id": "6bcc8115-3107-4eff-ba9d-e4a9bb9d3d71",
      "content": "<p>nervous about</p>"
    },
    {
      "id": "083a0171-a235-4f80-9ec5-813aa108f0da",
      "content": "<p>completed by</p>"
    },
    {
      "id": "c5042bdd-43a5-4dc1-97fb-cf6f3a096dc6",
      "content": "<p>delayed by</p>"
    },
    {
      "id": "595d80ad-b4c0-4c17-ba1f-8dda500b664c",
      "content": "<p>involved in</p>"
    }
  ],
  "correct_answer": [
    "D"
  ]
}